kusto_server.py
find_kusto_table_mcp-1.0.1.dist-info/licenses/LICENSE
kusto_mcp/__init__.py
kusto_mcp/__main__.py
kusto_mcp/enhanced_mcp_server.py
kusto_mcp/server_init.py
kusto_mcp/core/config.json
kusto_mcp/core/config.py
kusto_mcp/core/exceptions.py
kusto_mcp/core/logging_config.py
kusto_mcp/core/performance.py
kusto_mcp/core/resilience.py
kusto_mcp/mcp_tools/__init__.py
kusto_mcp/mcp_tools/analytics.py
kusto_mcp/mcp_tools/cache_management.py
kusto_mcp/mcp_tools/core_search.py
kusto_mcp/mcp_tools/data_export.py
kusto_mcp/mcp_tools/natural_language_query.py
kusto_mcp/mcp_tools/optimization.py
kusto_mcp/mcp_tools/prompts.py
kusto_mcp/mcp_tools/query_development.py
kusto_mcp/mcp_tools/query_execution.py
kusto_mcp/mcp_tools/resources.py
kusto_mcp/mcp_tools/templates.py
kusto_mcp/mcp_tools/verification.py
kusto_mcp/services/analytics_engine.py
kusto_mcp/services/kql_query_builder_service.py
kusto_mcp/services/query_handle_service.py
kusto_mcp/services/query_optimizer.py
kusto_mcp/services/query_template_service.py
kusto_mcp/services/query_templates.json
kusto_mcp/services/schema_cache_service.py
kusto_mcp/tools/ai_query_builder.py
kusto_mcp/tools/query_sampler.py
kusto_mcp/tools/query_sampler_simple.py
kusto_mcp/tools/table_discovery.py
kusto_mcp/utils/anti_hallucination.py
kusto_mcp/utils/helpers.py
kusto_mcp/utils/kusto_client.py
kusto_mcp/utils/prompt_loader.py
kusto_mcp/utils/sampling_client.py
prompts/README.md
prompts/azure_service_troubleshooting.md
prompts/data_discovery_assistant.md
prompts/discover_and_build_workflows.md
prompts/kusto_learning_assistant.md
prompts/kusto_livesight_assistant.md
prompts/kusto_query_optimizer.md
find_kusto_table_mcp-1.0.1.dist-info/METADATA
find_kusto_table_mcp-1.0.1.dist-info/WHEEL
find_kusto_table_mcp-1.0.1.dist-info/entry_points.txt
find_kusto_table_mcp-1.0.1.dist-info/top_level.txt
find_kusto_table_mcp-1.0.1.dist-info/RECORD
