Metadata-Version: 2.4
Name: find-kusto-table-mcp
Version: 1.0.1
Summary: Experimental Model Context Protocol (MCP) server for Kusto table discovery and query building
Author-email: Amelia Payne <ameliapayne@example.com>
License: MIT
Project-URL: Homepage, https://github.com/AmeliaRose802/find-kusto-table-mcp
Project-URL: Repository, https://github.com/AmeliaRose802/find-kusto-table-mcp
Project-URL: Documentation, https://github.com/AmeliaRose802/find-kusto-table-mcp/tree/master/docs
Project-URL: Bug Tracker, https://github.com/AmeliaRose802/find-kusto-table-mcp/issues
Keywords: mcp,kusto,azure-data-explorer,model-context-protocol,ai,analytics
Classifier: Development Status :: 4 - Beta
Classifier: Intended Audience :: Developers
Classifier: License :: OSI Approved :: MIT License
Classifier: Programming Language :: Python :: 3
Classifier: Programming Language :: Python :: 3.9
Classifier: Programming Language :: Python :: 3.10
Classifier: Programming Language :: Python :: 3.11
Classifier: Programming Language :: Python :: 3.12
Classifier: Topic :: Software Development :: Libraries :: Python Modules
Classifier: Topic :: Scientific/Engineering :: Information Analysis
Requires-Python: >=3.9
License-File: LICENSE
Requires-Dist: fastmcp>=2.12.0
Requires-Dist: jsonschema>=4.0.0
Requires-Dist: azure-kusto-data>=4.0.0
Requires-Dist: azure-identity>=1.14.0
Requires-Dist: matplotlib>=3.7.0
Requires-Dist: pandas>=2.0.0
Provides-Extra: dev
Requires-Dist: pytest>=7.4.0; extra == "dev"
Requires-Dist: pytest-asyncio>=0.21.0; extra == "dev"
Requires-Dist: pytest-cov>=4.1.0; extra == "dev"
Requires-Dist: pytest-benchmark>=4.0.0; extra == "dev"
Requires-Dist: black>=23.0.0; extra == "dev"
Requires-Dist: isort>=5.12.0; extra == "dev"
Requires-Dist: flake8>=6.0.0; extra == "dev"
Requires-Dist: mypy>=1.5.0; extra == "dev"
Requires-Dist: bandit>=1.7.5; extra == "dev"
Requires-Dist: safety>=2.3.0; extra == "dev"
Dynamic: license-file
